perfectconfig/__init__.py
perfectconfig/exceptions.py
perfectconfig/store.py
perfectconfig/types.py
perfectconfig-1.4.0.dist-info/METADATA
perfectconfig-1.4.0.dist-info/WHEEL
perfectconfig-1.4.0.dist-info/RECORD
