Metadata-Version: 2.4
Name: perfectconfig
Version: 1.4.0
Summary: Configuration Managment library
Project-URL: Homepage, https://conceivilize.com/products/perfectconfig
Project-URL: Documentation, https://readthedocs.org
Project-URL: Repository, https://github.com/supratikchatterjee16/perfectconfig.git
Project-URL: Bug Tracker, https://github.com/supratikchatterjee16/perfectconfig/issues
Project-URL: Changelog, https://github.com/supratikchatterjee16/iam/blob/master/CHANGELOG.md
Author-email: Supratik Chatterjee <supratikdevm96@gmail.com>
Maintainer-email: Supratik Chatterjee <supratikdevm96@gmail.com>
License: MIT License
Keywords: config,configuration,management
Classifier: Development Status :: 4 - Beta
Classifier: License :: OSI Approved :: MIT License
Classifier: Operating System :: OS Independent
Classifier: Programming Language :: Python :: 3.11
Classifier: Topic :: Software Development
Classifier: Topic :: System :: Filesystems
Requires-Python: >=3.9
Requires-Dist: appdirs
Requires-Dist: pyyaml
Requires-Dist: werkzeug
Provides-Extra: dev
Requires-Dist: black; extra == 'dev'
Requires-Dist: flake8; extra == 'dev'
Requires-Dist: isort; extra == 'dev'
Requires-Dist: mypy; extra == 'dev'
Requires-Dist: pytest; extra == 'dev'
Requires-Dist: pytest-cov; extra == 'dev'
